{"cameraMode":{"drawMode":0,"name":"Shaded","section":"Shading Mode"},"sceneLighting":true,"audioPlay":false,"sceneViewState":{"showFog":true,"showMaterialUpdate":false,"showSkybox":true,"showFlares":true,"showImageEffects":true,"showParticleSystems":true},"in2DMode":false,"pivot":{"x":0.04387752711772919,"y":-0.1900000125169754,"z":0.9031655788421631},"rotation":{"x":0.16942699253559113,"y":0.13553504645824433,"z":-0.02353048510849476,"w":0.9758950471878052},"size":1.5279271602630616,"orthographic":false}